cfmmc
