Metadata-Version: 1.1
Name: cfmmc
Version: 2017.12.5
Summary: 中国期货监控中心模拟浏览器操作
Home-page: https://github.com/lamter/cfmmc
Author: lamter
Author-email: lamter.fu@gmail.com
License: UNKNOWN
Keywords: cfmmc
Platform: UNKNOWN
Classifier: Programming Language :: Python :: 3.5
Classifier: Programming Language :: Python :: 3.6
Classifier: License :: OSI Approved :: MIT License
